flashvm-0.1.3.dist-info/METADATA
flashvm-0.1.3.dist-info/WHEEL
flashvm/__init__.py
flashvm/_core.abi3.so
flashvm/data/oci/blobs/sha256/376f0091e0391c04b324d131098738a61e3a83f35b671b1c67222accd5889d84
flashvm/data/oci/blobs/sha256/740873f52108333da8ea343b8e849a057f6913f9db8cfa3f0780f6029db93f21
flashvm/data/oci/blobs/sha256/923008ea115f01828b92822d9d6b7a538c768c9585e6275be11b1cb486cf5829
flashvm/data/oci/blobs/sha256/a10437c9ceddfb3b4a7a68eb3b58f0e17b9a3b2b7679ae27a0595cb1028b977e
flashvm/data/oci/blobs/sha256/a738260f1313692e8eb0b03f3c45446da1d6725d5d4f001a91c2c32fc0a84268
flashvm/data/oci/blobs/sha256/d9dcf90b1211120648a1e2a2a6b6a3f66f5727b67f15c759b6c547a949b5ea47
flashvm/data/oci/blobs/sha256/df603300ccbcc1523bc2760b1bd7133a04e098190156de2f216bc808a68a73a9
flashvm/data/oci/index.json
flashvm/data/oci/oci-layout
flashvm-0.1.3.dist-info/RECORD
