Metadata-Version: 2.4
Name: flashvm
Version: 0.1.3
Classifier: Development Status :: 3 - Alpha
Classifier: Intended Audience :: Developers
Classifier: License :: OSI Approved :: MIT License
Classifier: Programming Language :: Python :: 3
Classifier: Programming Language :: Python :: 3.8
Classifier: Programming Language :: Python :: 3.9
Classifier: Programming Language :: Python :: 3.10
Classifier: Programming Language :: Python :: 3.11
Classifier: Programming Language :: Python :: 3.12
Classifier: Programming Language :: Python :: 3.13
Classifier: Programming Language :: Rust
Requires-Dist: pytest>=7.0 ; extra == 'dev'
Requires-Dist: pytest-cov>=4.0 ; extra == 'dev'
Requires-Dist: pytest-timeout>=2.1 ; extra == 'dev'
Requires-Dist: pytest-xdist>=3.0 ; extra == 'dev'
Requires-Dist: pytest-benchmark>=4.0 ; extra == 'dev'
Requires-Dist: pytest-asyncio>=0.21 ; extra == 'dev'
Requires-Dist: pytest-mock>=3.10 ; extra == 'dev'
Requires-Dist: hypothesis>=6.75 ; extra == 'dev'
Requires-Dist: maturin>=1.0,<2.0 ; extra == 'dev'
Requires-Dist: pytest>=7.0 ; extra == 'test'
Requires-Dist: pytest-cov>=4.0 ; extra == 'test'
Requires-Dist: pytest-timeout>=2.1 ; extra == 'test'
Provides-Extra: dev
Provides-Extra: test
Summary: Run Python code inside libkrun microVMs, with an embedded offline OCI image
Keywords: python,vm,isolation,libkrun,krunvm,oci,skopeo
Home-Page: https://github.com/fullzer4/flashvm
Author-email: fullzer4 <fullzer4@example.com>
License: MIT
Requires-Python: >=3.8
Project-URL: Repository, https://github.com/fullzer4/flashvm
